quickmongo/Base.py
quickmongo/Exception.py
quickmongo/Util.py
quickmongo/__init__.py
quickmongo.py-1.0.0.dist-info/LICENSE
quickmongo.py-1.0.0.dist-info/METADATA
quickmongo.py-1.0.0.dist-info/WHEEL
quickmongo.py-1.0.0.dist-info/top_level.txt
quickmongo.py-1.0.0.dist-info/RECORD
