Metadata-Version: 2.1
Name: quickmongo.py
Version: 1.0.0
Summary: A simple and quick wrapper for pymongo!
Home-page: https://github.com/Scientific-Guy/quickmongo.py
License: MIT
Keywords: quickmongo.py
Platform: UNKNOWN
Classifier: License :: OSI Approved :: MIT License
Classifier: Programming Language :: Python :: 3
Classifier: Programming Language :: Python :: 3.7
